rethinkdc/__init__.py
rethinkdc/imagenet_ipc.py
rethinkdc/train_KD.py
rethinkdc/utils.py
rethinkdc/utils_fkd.py
rethinkdc/dc_config/standard_hard_config.yaml
rethinkdc/dc_config/standard_soft_config.yaml
rethinkdc-0.3.2.dist-info/METADATA
rethinkdc-0.3.2.dist-info/WHEEL
rethinkdc-0.3.2.dist-info/entry_points.txt
rethinkdc-0.3.2.dist-info/top_level.txt
rethinkdc-0.3.2.dist-info/RECORD
