Metadata-Version: 2.2
Name: rethinkdc
Version: 0.3.2
Summary: Rethinkinig Large-scale Dataset Compression
Author: Lingao Xiao
Author-email: xiao_lingao@u.nus.edu
License: MIT
Keywords: dataset compression,deep learning,machine learning
Classifier: Development Status :: 3 - Alpha
Classifier: Intended Audience :: Developers
Classifier: Intended Audience :: Science/Research
Classifier: Programming Language :: Python :: 3
Classifier: Programming Language :: Python :: 3.10
Classifier: Programming Language :: Python :: 3.11
Classifier: Programming Language :: Python :: 3.12
Classifier: Topic :: Scientific/Engineering :: Artificial Intelligence
Requires-Python: >=3.10
Requires-Dist: torch>=2.0.0
Requires-Dist: torchvision>=0.15.0
Requires-Dist: torchaudio>=2.0.0
Requires-Dist: numpy>=2.0
Requires-Dist: wandb>=0.19
Requires-Dist: rich>=13.9
Requires-Dist: huggingface-hub>=0.28
Requires-Dist: datasets>=3.2
Requires-Dist: pyyaml>=6.0
Dynamic: author
Dynamic: author-email
Dynamic: classifier
Dynamic: description
Dynamic: description-content-type
Dynamic: keywords
Dynamic: license
Dynamic: requires-dist
Dynamic: requires-python
Dynamic: summary
